.DS_Store
cdf_ifs_file_extractor/__init__.py
cdf_ifs_file_extractor/__main__.py
cdf_ifs_file_extractor/_version.py
cdf_ifs_file_extractor/business_logic.py
cdf_ifs_file_extractor/file_uploader.py
cdf_ifs_file_extractor/helper.py
cdf_ifs_file_extractor/monitoring.py
cdf_ifs_file_extractor/utils.py
cdf_ifs_file_extractor/winservice.py
tests/__init__.py
tests/test_business_logic.py
tests/test_utils.py
cdf_ifs_file_extractor-0.1.2.dist-info/LICENSE
cdf_ifs_file_extractor-0.1.2.dist-info/METADATA
cdf_ifs_file_extractor-0.1.2.dist-info/WHEEL
cdf_ifs_file_extractor-0.1.2.dist-info/top_level.txt
cdf_ifs_file_extractor-0.1.2.dist-info/RECORD
