Metadata-Version: 2.1
Name: cdf-ifs-file-extractor
Version: 0.1.2
Summary: Python package for extracting files from IFS to CDF. Copyright 2020 Cognite AS
Home-page: UNKNOWN
Author: Cognite
Author-email: jonas.mack@cognite.com
License: UNKNOWN
Platform: UNKNOWN
Classifier: Development Status :: 4 - Beta
Classifier: Intended Audience :: Developers
Classifier: Intended Audience :: System Administrators
Classifier: Natural Language :: English
Requires-Python: >=3.5
Requires-Dist: cognite-sdk (>=1.1.0)
Requires-Dist: google-cloud-logging (>=1.12.1)
Requires-Dist: cognite-prometheus (>=0.1.0)
Requires-Dist: pyyaml (>=5.1.0)
